crawlerdetect/__init__.py
crawlerdetect/cli.py
crawlerdetect/crawlerdetect.py
crawlerdetect/providers/__init__.py
crawlerdetect/providers/crawlers.py
crawlerdetect/providers/exclusions.py
crawlerdetect/providers/headers.py
crawlerdetect-0.3.0.dist-info/LICENSE
crawlerdetect-0.3.0.dist-info/METADATA
crawlerdetect-0.3.0.dist-info/WHEEL
crawlerdetect-0.3.0.dist-info/entry_points.txt
crawlerdetect-0.3.0.dist-info/RECORD
