Metadata-Version: 2.1
Name: crawlerdetect
Version: 0.3.0
Summary: CrawlerDetect is a Python library designed to identify bots, crawlers, and spiders by analyzing their user agents.
Home-page: https://github.com/moskrc/crawlerdetect
License: MIT
Keywords: crawler,crawler detect,crawler detector,crawlerdetect,python crawler detect
Author: Vitalii Shishorin
Author-email: moskrc@gmail.com
Requires-Python: >=3.9,<4
Classifier: License :: OSI Approved :: MIT License
Classifier: Programming Language :: Python :: 3
Classifier: Programming Language :: Python :: 3.9
Classifier: Programming Language :: Python :: 3.10
Classifier: Programming Language :: Python :: 3.11
Classifier: Programming Language :: Python :: 3.12
Project-URL: Documentation, https://github.com/moskrc/crawlerdetect
Project-URL: Repository, https://github.com/moskrc/crawlerdetect
